digestdb/__init__.py
digestdb/database.py
digestdb/hashify.py
digestdb/model.py
digestdb-0.0.1a1.dist-info/DESCRIPTION.rst
digestdb-0.0.1a1.dist-info/METADATA
digestdb-0.0.1a1.dist-info/RECORD
digestdb-0.0.1a1.dist-info/WHEEL
digestdb-0.0.1a1.dist-info/metadata.json
digestdb-0.0.1a1.dist-info/top_level.txt
