Metadata-Version: 2.0
Name: digestdb
Version: 0.0.1a1
Summary: digestdb is a database for storing binary data in a balanced set of file system directories and providing access to this data via tradiational database style (e.g. SQL) access.
Home-page: https://github.com/claws/digestdb
Author: Chris Laws
Author-email: clawsicus@gmail.com
License: MPL 2.0
Keywords: hash database development
Platform: UNKNOWN
Classifier: Development Status :: 3 - Alpha
Classifier: Intended Audience :: Developers
Classifier: License :: OSI Approved :: Mozilla Public License 2.0 (MPL 2.0)
Classifier: Programming Language :: Python :: 3.5
Requires-Dist: SQLAlchemy (>=1.0.8)
Provides-Extra: dev
Requires-Dist: autopep8; extra == 'dev'
Requires-Dist: pep8; extra == 'dev'
Requires-Dist: sphinx; extra == 'dev'
Provides-Extra: test
Requires-Dist: coverage; extra == 'test'
